aett/domain/__init__.py
aett/domain/aggregate.py
aett/domain/aggregate_repository.py
aett/domain/async_aggregate_repository.py
aett/domain/async_default_aggregate_repository.py
aett/domain/async_default_saga_repository.py
aett/domain/async_saga_repository.py
aett/domain/conflict_delegate.py
aett/domain/conflict_detector.py
aett/domain/conflicting_commit_exception.py
aett/domain/constants.py
aett/domain/default_aggregate_repository.py
aett/domain/default_saga_repository.py
aett/domain/duplicate_commit_exception.py
aett/domain/non_conflicting_commit_exception.py
aett/domain/saga.py
aett/domain/saga_repository.py
aett_domain-2.1.0.dist-info/LICENSE
aett_domain-2.1.0.dist-info/METADATA
aett_domain-2.1.0.dist-info/WHEEL
aett_domain-2.1.0.dist-info/top_level.txt
aett_domain-2.1.0.dist-info/RECORD
