Metadata-Version: 2.1
Name: aett-domain
Version: 2.1.0
Summary: Domain modeling types aett event store
Author-email: Jacob Reimers <pypi@reimers.io>
License: MIT License
Project-URL: Homepage, https://github.com/jjrdk/aett
Keywords: events,event store,ddd,domain
Classifier: License :: OSI Approved :: MIT License
Classifier: Programming Language :: Python
Classifier: Programming Language :: Python :: 3
Requires-Python: >=3.10
License-File: LICENSE
Requires-Dist: multipledispatch>=1.0.0
Requires-Dist: aett-eventstore>=2.1.0
Provides-Extra: dev
Requires-Dist: pip-tools; extra == "dev"
Requires-Dist: pytest; extra == "dev"
Requires-Dist: behave; extra == "dev"
